fetchit/__init__.py
fetchit/_version.py
fetchit/welcome.py
fetchit/utils/__init__.py
fetchit/utils/show_versions.py
fetchit-0.0.2.dist-info/LICENSE
fetchit-0.0.2.dist-info/METADATA
fetchit-0.0.2.dist-info/WHEEL
fetchit-0.0.2.dist-info/top_level.txt
fetchit-0.0.2.dist-info/RECORD
